langchain_tavily/.github/workflows/test.yml
langchain_tavily/__init__.py
langchain_tavily/_utilities.py
langchain_tavily/py.typed
langchain_tavily/tavily_crawl.py
langchain_tavily/tavily_extract.py
langchain_tavily/tavily_map.py
langchain_tavily/tavily_research.py
langchain_tavily/tavily_search.py
langchain_tavily-0.2.14.dist-info/LICENSE
langchain_tavily-0.2.14.dist-info/METADATA
langchain_tavily-0.2.14.dist-info/WHEEL
langchain_tavily-0.2.14.dist-info/RECORD
