Metadata-Version: 2.3
Name: langchain-tavily
Version: 0.2.14
Summary: An integration package connecting Tavily and LangChain
License: MIT
Requires-Python: >=3.10,<4.0
Classifier: License :: OSI Approved :: MIT License
Classifier: Programming Language :: Python :: 3
Classifier: Programming Language :: Python :: 3.10
Classifier: Programming Language :: Python :: 3.11
Classifier: Programming Language :: Python :: 3.12
Classifier: Programming Language :: Python :: 3.13
Requires-Dist: aiohttp (>=3.11.14,<4.0.0)
Requires-Dist: langchain (>=0.3.20,<2.0.0)
Requires-Dist: langchain-core (>=0.3.15,<2.0.0)
Requires-Dist: requests (>=2.32.3,<3.0.0)
Project-URL: Repository, https://github.com/tavily-ai/langchain-tavily
